r82labs_analytics/__init__.py
r82labs_analytics/data_cleaning.py
r82labs_analytics-0.1.0.dist-info/METADATA
r82labs_analytics-0.1.0.dist-info/WHEEL
r82labs_analytics-0.1.0.dist-info/licenses/LICENSE
r82labs_analytics-0.1.0.dist-info/RECORD
