Metadata-Version: 2.4
Name: r82labs-analytics
Version: 0.1.0
Summary: 
License-File: LICENSE
Author: r82labs-ronan
Author-email: ronan@r82labs.com
Requires-Python: >=3.13
Classifier: Programming Language :: Python :: 3
Classifier: Programming Language :: Python :: 3.13
Classifier: Programming Language :: Python :: 3.14
Requires-Dist: polars (>=1.33.1,<2.0.0)
